LICENSE
MANIFEST.in
README.rst
setup.py
django_frontend_template.egg-info/PKG-INFO
django_frontend_template.egg-info/SOURCES.txt
django_frontend_template.egg-info/dependency_links.txt
django_frontend_template.egg-info/not-zip-safe
django_frontend_template.egg-info/top_level.txt
djfrontend/__init__.py
djfrontend/templates/djfrontend/base.html
djfrontend/templatetags/__init__.py
djfrontend/templatetags/djfrontend.py
docs/Makefile
docs/make.bat
docs/build/doctrees/changelog.doctree
docs/build/doctrees/environment.pickle
docs/build/doctrees/getting_started.doctree
docs/build/doctrees/index.doctree
docs/build/doctrees/license.doctree
docs/build/doctrees/road_map.doctree
docs/build/doctrees/template_blocks.doctree
docs/build/doctrees/template_tags.doctree
docs/build/html/.buildinfo
docs/build/html/changelog.html
docs/build/html/genindex.html
docs/build/html/getting_started.html
docs/build/html/index.html
docs/build/html/license.html
docs/build/html/objects.inv
docs/build/html/road_map.html
docs/build/html/search.html
docs/build/html/searchindex.js
docs/build/html/template_blocks.html
docs/build/html/template_tags.html
docs/build/html/_sources/changelog.txt
docs/build/html/_sources/getting_started.txt
docs/build/html/_sources/index.txt
docs/build/html/_sources/license.txt
docs/build/html/_sources/road_map.txt
docs/build/html/_sources/template_blocks.txt
docs/build/html/_sources/template_tags.txt
docs/build/html/_static/ajax-loader.gif
docs/build/html/_static/basic.css
docs/build/html/_static/comment-bright.png
docs/build/html/_static/comment-close.png
docs/build/html/_static/comment.png
docs/build/html/_static/default.css
docs/build/html/_static/doctools.js
docs/build/html/_static/down-pressed.png
docs/build/html/_static/down.png
docs/build/html/_static/file.png
docs/build/html/_static/jquery.js
docs/build/html/_static/minus.png
docs/build/html/_static/plus.png
docs/build/html/_static/pygments.css
docs/build/html/_static/searchtools.js
docs/build/html/_static/sidebar.js
docs/build/html/_static/underscore.js
docs/build/html/_static/up-pressed.png
docs/build/html/_static/up.png
docs/build/html/_static/websupport.js
docs/source/changelog.rst
docs/source/conf.py
docs/source/getting_started.rst
