Metadata-Version: 1.0
Name: django-frontend-template
Version: 1.1.0
Summary: A basic Django template built on HTML5 Boilerplate.
Home-page: http://github.com/jonfaustman/django-frontend-template
Author: Jon Faustman
Author-email: jon@faustman.org
License: MIT
Platform: UNKNOWN
Classifier: Development Status :: 5 - Production/Stable
Classifier: Environment :: Web Environment
Classifier: Intended Audience :: End Users/Desktop
Classifier: Natural Language :: English
Classifier: Operating System :: OS Independent
Classifier: Framework :: Django
Classifier: Programming Language :: Python
Classifier: Topic :: Internet :: WWW/HTTP :: Dynamic Content :: CGI Tools/Libraries
Classifier: Topic :: Utilities
Classifier: License :: OSI Approved :: MIT License
